datalad_gooey/__init__.py
datalad_gooey/__main__.py
datalad_gooey/_version.py
datalad_gooey/active_suite.py
datalad_gooey/annex_metadata.py
datalad_gooey/api_utils.py
datalad_gooey/app.py
datalad_gooey/askpass.py
datalad_gooey/cmd_actions.py
datalad_gooey/complete_api.py
datalad_gooey/conftest.py
datalad_gooey/constraints.py
datalad_gooey/credentials.py
datalad_gooey/datalad_ui.py
datalad_gooey/dataladcmd_exec.py
datalad_gooey/dataladcmd_ui.py
datalad_gooey/flowlayout.py
datalad_gooey/fsbrowser.py
datalad_gooey/fsbrowser_item.py
datalad_gooey/gooey.py
datalad_gooey/history_widget.py
datalad_gooey/lsdir.py
datalad_gooey/metadata_editor_base.py
datalad_gooey/metadata_widget.py
datalad_gooey/param.py
datalad_gooey/param_alt.py
datalad_gooey/param_form_utils.py
datalad_gooey/param_multival.py
datalad_gooey/param_path.py
datalad_gooey/param_widgets.py
datalad_gooey/postinstall.py
datalad_gooey/property_widget.py
datalad_gooey/resource_provider.py
datalad_gooey/simplified_api.py
datalad_gooey/status_light.py
datalad_gooey/utility_actions.py
datalad_gooey/utils.py
datalad_gooey/patches/__init__.py
datalad_gooey/patches/clone.py
datalad_gooey/resources/desktop/datalad-gooey.desktop
datalad_gooey/resources/icons/absent.svg
datalad_gooey/resources/icons/app_icon_32.svg
datalad_gooey/resources/icons/clean.svg
datalad_gooey/resources/icons/datalad_gooey_logo.svg
datalad_gooey/resources/icons/dataset-closed.svg
datalad_gooey/resources/icons/directory-closed.svg
datalad_gooey/resources/icons/file-annex.svg
datalad_gooey/resources/icons/file-git.svg
datalad_gooey/resources/icons/file-or-directory.svg
datalad_gooey/resources/icons/file.svg
datalad_gooey/resources/icons/kaboom.svg
datalad_gooey/resources/icons/modified.svg
datalad_gooey/resources/icons/untracked.svg
datalad_gooey/resources/ui/credentials_dialog.ui
datalad_gooey/resources/ui/main_window.ui
datalad_gooey/resources/ui/user_dialog.ui
datalad_gooey/tests/__init__.py
datalad_gooey/tests/test_constraints.py
datalad_gooey-0.2.0.dist-info/LICENSE
datalad_gooey-0.2.0.dist-info/METADATA
datalad_gooey-0.2.0.dist-info/WHEEL
datalad_gooey-0.2.0.dist-info/entry_points.txt
datalad_gooey-0.2.0.dist-info/top_level.txt
datalad_gooey-0.2.0.dist-info/RECORD
