Metadata-Version: 2.1
Name: datalad-gooey
Version: 0.2.0
Summary: A simple GUI for DataLad
Home-page: https://github.com/datalad/datalad-gooey
Author: The DataLad Team and Contributors
Author-email: team@datalad.org
License: MIT
Platform: UNKNOWN
Classifier: Programming Language :: Python
Classifier: License :: OSI Approved :: BSD License
Classifier: Programming Language :: Python :: 3
Requires-Python: >=3.7
License-File: LICENSE
Requires-Dist: datalad (>=0.17.6)
Requires-Dist: datalad-next (>=0.6.2)
Requires-Dist: outdated
Requires-Dist: pyqtdarktheme
Requires-Dist: pyside6
Requires-Dist: applescript ; platform_system == "Darwin"
Provides-Extra: devel
Requires-Dist: coverage ; extra == 'devel'
Requires-Dist: pytest ; extra == 'devel'
Requires-Dist: pytest-cov ; extra == 'devel'
Requires-Dist: pytest-qt ; extra == 'devel'
Requires-Dist: pytest-xvfb ; extra == 'devel'
